setup.py
oulumetrics/__init__.py
oulumetrics/metrics.py
oulumetrics.egg-info/PKG-INFO
oulumetrics.egg-info/SOURCES.txt
oulumetrics.egg-info/dependency_links.txt
oulumetrics.egg-info/not-zip-safe
oulumetrics.egg-info/top_level.txt