Metadata-Version: 1.0
Name: oulumetrics
Version: 0.1
Summary: oulu-npu database metrics implementations (APCER, BPCER, ACER)
Home-page: UNKNOWN
Author: Guilherme Baldo Carlos
Author-email: guilhermebaldocarlos@gmail.com
License: UNKNOWN
Platform: UNKNOWN
